annflux/__init__.py
annflux-0.0.0.dist-info/METADATA
annflux-0.0.0.dist-info/WHEEL
annflux-0.0.0.dist-info/top_level.txt
annflux-0.0.0.dist-info/RECORD
