Metadata-Version: 2.1
Name: annflux
Version: 0.0.0
Summary: Coming soon
Author-email: Laurens Hogeweg <l.hogeweg@gmail.com>
